{
    "relationships": [
        {
            "relationshipId": 1,
            "otherEntityName": "event",
            "relationshipType": "many-to-many",
            "otherEntityNameCapitalized": "Event",
            "ownerSide": false
        },
        {
            "relationshipId": 2,
            "otherEntityName": "article",
            "relationshipType": "many-to-many",
            "otherEntityNameCapitalized": "Article",
            "ownerSide": false
        }
    ],
    "fields": [
        {
            "fieldId": 1,
            "fieldName": "name",
            "fieldType": "String",
            "fieldNameCapitalized": "Name",
            "fieldNameUnderscored": "name"
        },
        {
            "fieldId": 2,
            "fieldName": "email",
            "fieldType": "String",
            "fieldNameCapitalized": "Email",
            "fieldNameUnderscored": "email"
        },
        {
            "fieldId": 3,
            "fieldName": "telephone",
            "fieldType": "String",
            "fieldNameCapitalized": "Telephone",
            "fieldNameUnderscored": "telephone"
        },
        {
            "fieldId": 4,
            "fieldName": "location",
            "fieldType": "String",
            "fieldNameCapitalized": "Location",
            "fieldNameUnderscored": "location"
        },
        {
            "fieldId": 5,
            "fieldName": "website",
            "fieldType": "String",
            "fieldNameCapitalized": "Website",
            "fieldNameUnderscored": "website"
        },
        {
            "fieldId": 6,
            "fieldName": "details",
            "fieldType": "String",
            "fieldNameCapitalized": "Details",
            "fieldNameUnderscored": "details"
        }
    ],
    "fieldsContainOwnerManyToMany": false,
    "fieldsContainOneToMany": false,
    "fieldsContainLocalDate": false,
    "fieldsContainCustomTime": false,
    "fieldsContainBigDecimal": false,
    "fieldsContainDateTime": false,
    "changelogDate": "20150118210203"
}